fancy_formset/__init__.py
fancy_formset/formsets.py
fancy_formset/static/fancy_formset/formset.css
fancy_formset/static/fancy_formset/formset.js
fancy_formset/static/fancy_formset/formset.min.css
fancy_formset/static/fancy_formset/formset.module.js
fancy_formset/templates/fancy_formset/default.html
fancy_formset/templates/fancy_formset/div.html
fancy_formset/templates/fancy_formset/p.html
fancy_formset/templates/fancy_formset/table.html
fancy_formset/templates/fancy_formset/ul.html
django_fancy_formset-1.0.0.dist-info/LICENSE
django_fancy_formset-1.0.0.dist-info/METADATA
django_fancy_formset-1.0.0.dist-info/WHEEL
django_fancy_formset-1.0.0.dist-info/top_level.txt
django_fancy_formset-1.0.0.dist-info/RECORD
