Metadata-Version: 2.1
Name: django-fancy-formset
Version: 1.0.0
Summary: A Django app and pure JavaScript library to manage formsets
Author-email: Richard Terry <code@radiac.net>
Project-URL: Homepage, https://radiac.net/projects/django-fancy-formset/
Project-URL: Documentation, https://django-fancy-formset.readthedocs.io/en/latest/
Project-URL: Source, https://github.com/radiac/django-fancy-formset
Project-URL: NPM, https://www.npmjs.com/package/django-fancy-formset
Project-URL: Bug Tracker, https://github.com/radiac/django-fancy-formset/issues
Keywords: django,formset
Classifier: Development Status :: 4 - Beta
Classifier: Framework :: Django
Classifier: License :: OSI Approved :: BSD License
Classifier: Programming Language :: Python :: 3
Classifier: Operating System :: OS Independent
Requires-Python: >=3.7
License-File: LICENSE
Requires-Dist: Django (>=2.2)
